bentley_ottmann/__init__.py
bentley_ottmann/planar.py
bentley_ottmann/py.typed
bentley_ottmann/_core/__init__.py
bentley_ottmann/_core/base.py
bentley_ottmann/_core/event.py
bentley_ottmann/_core/events_queue_key.py
bentley_ottmann/_core/events_registry.py
bentley_ottmann/_core/hints.py
bentley_ottmann/_core/sweep_line_key.py
bentley_ottmann/_core/utils.py
bentley_ottmann-9.0.1.dist-info/licenses/LICENSE
bentley_ottmann-9.0.1.dist-info/METADATA
bentley_ottmann-9.0.1.dist-info/WHEEL
bentley_ottmann-9.0.1.dist-info/top_level.txt
bentley_ottmann-9.0.1.dist-info/RECORD
